python_project_boilerplate/__init__.py
python_project_boilerplate/python_project_boilerplate.py
python_project_boilerplate-1.0.0.dist-info/METADATA
python_project_boilerplate-1.0.0.dist-info/WHEEL
python_project_boilerplate-1.0.0.dist-info/entry_points.txt
python_project_boilerplate-1.0.0.dist-info/top_level.txt
python_project_boilerplate-1.0.0.dist-info/RECORD
