Metadata-Version: 2.1
Name: python-project-boilerplate
Version: 1.0.0
Summary: Package to create data python_project_structure
Author: Pankaj Kalal
Author-email: pankajgkalal@gmail.com
License: UNKNOWN
Platform: UNKNOWN
Classifier: Programming Language :: Python :: 3
Classifier: License :: OSI Approved :: MIT License
Classifier: Operating System :: OS Independent
Requires-Python: >=3.7
